CHANGES.rst
MANIFEST.in
README.rst
setup.py
src/__init__.py
src/tc.py
src/tests/__init__.py
src/tests/test_tarjan.py
src/tests/test_tc.py
tarjan.egg-info/PKG-INFO
tarjan.egg-info/SOURCES.txt
tarjan.egg-info/dependency_links.txt
tarjan.egg-info/top_level.txt
tarjan.egg-info/zip-safe