Metadata-Version: 1.1
Name: tarjan
Version: 0.2.3
Summary: Implementation of Tarjan's algorithm: resolve cyclic deps
Home-page: http://github.com/bwesterb/py-tarjan/
Author: Bas Westerbaan
Author-email: bas@westerbaan.name
License: UNKNOWN
Platform: UNKNOWN
Classifier: Development Status :: 5 - Production/Stable
Classifier: License :: OSI Approved :: GNU General Public License v3 (GPLv3)
Classifier: Programming Language :: Python :: 2.6
Classifier: Programming Language :: Python :: 2.7
Classifier: Programming Language :: Python :: 3.2
Classifier: Programming Language :: Python :: 3.3
